ysd_test/__init__.py
ysd_test/__main__.py
ysd_test/main.py
ysd_test-1.1.1.dist-info/LICENSE
ysd_test-1.1.1.dist-info/METADATA
ysd_test-1.1.1.dist-info/WHEEL
ysd_test-1.1.1.dist-info/entry_points.txt
ysd_test-1.1.1.dist-info/RECORD
