Metadata-Version: 2.1
Name: ysd_test
Version: 1.1.1
Summary: test
Home-page: https://github.com/top-maker/ysd-test
Author: Ying Shaodong
Author-email: fhelloysd@gmail.com
Requires-Python: >=3.8,<4.0
Classifier: Programming Language :: Python :: 3
Classifier: Programming Language :: Python :: 3.8
Classifier: Programming Language :: Python :: 3.9
Classifier: Programming Language :: Python :: 3.10
Classifier: Programming Language :: Python :: 3.11
Classifier: Programming Language :: Python :: 3.12
Project-URL: Documentation, https://top-maker.github.io/ysd-test/
Project-URL: Repository, https://github.com/top-maker/ysd-test
